pycrires/__init__.py
pycrires/_version.py
pycrires/keywords.txt
pycrires/pipeline.py
pycrires/util.py
pycrires/calib_data/H1559.dat
pycrires/calib_data/H1567.dat
pycrires/calib_data/H1575.dat
pycrires/calib_data/H1582.dat
pycrires/calib_data/J1226.dat
pycrires/calib_data/J1228.dat
pycrires/calib_data/J1232.dat
pycrires/calib_data/K2148.dat
pycrires/calib_data/K2166.dat
pycrires/calib_data/K2192.dat
pycrires/calib_data/K2217.dat
pycrires/calib_data/L3244.dat
pycrires/calib_data/L3262.dat
pycrires/calib_data/L3302.dat
pycrires/calib_data/L3340.dat
pycrires/calib_data/L3377.dat
pycrires/calib_data/L3412.dat
pycrires/calib_data/L3426.dat
pycrires/calib_data/M4187.dat
pycrires/calib_data/M4211.dat
pycrires/calib_data/M4266.dat
pycrires/calib_data/M4318.dat
pycrires/calib_data/M4368.dat
pycrires/calib_data/M4416.dat
pycrires/calib_data/M4461.dat
pycrires/calib_data/M4504.dat
pycrires/calib_data/M4519.dat
pycrires/calib_data/Y1028.dat
pycrires/calib_data/Y1029.dat
pycrires/calib_data/lines_thar.txt
pycrires/calib_data/lines_u_redman.txt
pycrires/calib_data/lines_u_sarmiento.txt
pycrires-0.4.4.dist-info/licenses/LICENSE
pycrires-0.4.4.dist-info/METADATA
pycrires-0.4.4.dist-info/WHEEL
pycrires-0.4.4.dist-info/top_level.txt
pycrires-0.4.4.dist-info/RECORD
