Metadata-Version: 2.4
Name: pycrires
Version: 0.4.4
Summary: Data reduction pipeline for VLT/CRIRES+
Author-email: Tomas Stolker <stolker@strw.leidenuniv.nl>, Rico Landman <rlandman@strw.leidenuniv.nl>
License-Expression: MIT
Project-URL: Documentation, https://pycrires.readthedocs.io
Project-URL: Repository, https://github.com/tomasstolker/pycrires
Project-URL: Issues, https://github.com/tomasstolker/pycrires/issues
Classifier: Programming Language :: Python :: 3.11
Classifier: Programming Language :: Python :: 3.12
Classifier: Programming Language :: Python :: 3.13
Classifier: Intended Audience :: Science/Research
Classifier: Topic :: Scientific/Engineering :: Astronomy
Requires-Python: <3.14,>=3.11
License-File: LICENSE
Requires-Dist: astropy
Requires-Dist: astroquery
Requires-Dist: beartype
Requires-Dist: matplotlib
Requires-Dist: numpy
Requires-Dist: openpyxl
Requires-Dist: pandas
Requires-Dist: pooch
Requires-Dist: scikit-image
Requires-Dist: scipy
Requires-Dist: skycalc_ipy
Requires-Dist: tqdm
Provides-Extra: docs
Requires-Dist: jupyter; extra == "docs"
Requires-Dist: nbconvert; extra == "docs"
Requires-Dist: nbsphinx; extra == "docs"
Requires-Dist: pandoc; extra == "docs"
Requires-Dist: pydata-sphinx-theme; extra == "docs"
Requires-Dist: sphinx; extra == "docs"
Requires-Dist: sphinx-automodapi; extra == "docs"
Requires-Dist: sphinxawesome-theme; extra == "docs"
Provides-Extra: test
Requires-Dist: black; extra == "test"
Requires-Dist: flake8; extra == "test"
Requires-Dist: pycodestyle; extra == "test"
Requires-Dist: pylint; extra == "test"
Requires-Dist: pytest; extra == "test"
Requires-Dist: pytest-cov; extra == "test"
Dynamic: license-file
